claims/__init__.py
claims/ability.py
claims/claim.py
claims/claim_set.py
claims/errors.py
claims/parsing.py
claims/py.typed
claims-0.3.0.dist-info/LICENSE.txt
claims-0.3.0.dist-info/METADATA
claims-0.3.0.dist-info/README.md
claims-0.3.0.dist-info/WHEEL
claims-0.3.0.dist-info/top_level.txt
claims-0.3.0.dist-info/RECORD
