Metadata-Version: 2.1
Name: claims
Version: 0.3.0
Summary: Port of https://github.com/eturino/claims.ts. Library to manage claims and permissions.
Home-page: https://github.com/eturino/claims.py
Author: Eduardo Turiño
Author-email: eturino@eturino.com
License: Apache 2.0
Keywords: claims permissions
Classifier: Development Status :: 4 - Beta
Classifier: Intended Audience :: Developers
Classifier: Natural Language :: English
Classifier: License :: OSI Approved :: Apache Software License
Classifier: Programming Language :: Python
Classifier: Programming Language :: Python :: 3.6
Classifier: Programming Language :: Python :: 3.7
Classifier: Programming Language :: Python :: 3.8
Classifier: Programming Language :: Python :: 3.9
Requires-Python: >= 3.6
License-File: LICENSE.txt
License-File: README.md
Requires-Dist: pydantic <3,>=2.4
Requires-Dist: key-set
